[
    {
      "inputs": [
        {
          "internalType": "address",
          "name": "degen_",
          "type": "address"
        },
        {
          "internalType": "address",
          "name": "weth_",
          "type": "address"
        },
        {
          "internalType": "uint256",
          "name": "fee_",
          "type": "uint256"
        },
        {
          "internalType": "bytes32",
          "name": "keyHash_",
          "type": "bytes32"
        },
        {
          "internalType": "address",
          "name": "vrfCoordinator",
          "type": "address"
        },
        {
          "internalType": "address",
          "name": "linkToken",
          "type": "address"
        }
      ],
      "stateMutability": "nonpayable",
      "type": "constructor"
    },
    {
      "anonymous": false,
      "inputs": [
        {
          "indexed": true,
          "internalType": "address",
          "name": "previousOwner",
          "type": "address"
        },
        {
          "indexed": true,
          "internalType": "address",
          "name": "newOwner",
          "type": "address"
        }
      ],
      "name": "OwnershipTransferred",
      "type": "event"
    },
    {
      "anonymous": false,
      "inputs": [
        {
          "indexed": false,
          "internalType": "address",
          "name": "account",
          "type": "address"
        }
      ],
      "name": "Paused",
      "type": "event"
    },
    {
      "anonymous": false,
      "inputs": [
        {
          "indexed": false,
          "internalType": "address",
          "name": "account",
          "type": "address"
        }
      ],
      "name": "Unpaused",
      "type": "event"
    },
    {
      "inputs": [
        {
          "internalType": "bytes32",
          "name": "",
          "type": "bytes32"
        }
      ],
      "name": "betPlaced",
      "outputs": [
        {
          "internalType": "address",
          "name": "user",
          "type": "address"
        },
        {
          "internalType": "uint256",
          "name": "amount",
          "type": "uint256"
        }
      ],
      "stateMutability": "view",
      "type": "function"
    },
    {
      "inputs": [
        {
          "internalType": "bytes32",
          "name": "",
          "type": "bytes32"
        }
      ],
      "name": "betResolved",
      "outputs": [
        {
          "internalType": "bool",
          "name": "",
          "type": "bool"
        }
      ],
      "stateMutability": "view",
      "type": "function"
    },
    {
      "inputs": [],
      "name": "owner",
      "outputs": [
        {
          "internalType": "address",
          "name": "",
          "type": "address"
        }
      ],
      "stateMutability": "view",
      "type": "function"
    },
    {
      "inputs": [],
      "name": "paused",
      "outputs": [
        {
          "internalType": "bool",
          "name": "",
          "type": "bool"
        }
      ],
      "stateMutability": "view",
      "type": "function"
    },
    {
      "inputs": [],
      "name": "pool",
      "outputs": [
        {
          "internalType": "uint256",
          "name": "",
          "type": "uint256"
        }
      ],
      "stateMutability": "view",
      "type": "function"
    },
    {
      "inputs": [
        {
          "internalType": "bytes32",
          "name": "requestId",
          "type": "bytes32"
        },
        {
          "internalType": "uint256",
          "name": "randomness",
          "type": "uint256"
        }
      ],
      "name": "rawFulfillRandomness",
      "outputs": [],
      "stateMutability": "nonpayable",
      "type": "function"
    },
    {
      "inputs": [],
      "name": "renounceOwnership",
      "outputs": [],
      "stateMutability": "nonpayable",
      "type": "function"
    },
    {
      "inputs": [
        {
          "internalType": "address",
          "name": "newOwner",
          "type": "address"
        }
      ],
      "name": "transferOwnership",
      "outputs": [],
      "stateMutability": "nonpayable",
      "type": "function"
    },
    {
      "inputs": [
        {
          "internalType": "address",
          "name": "",
          "type": "address"
        }
      ],
      "name": "winAmount",
      "outputs": [
        {
          "internalType": "uint256",
          "name": "",
          "type": "uint256"
        }
      ],
      "stateMutability": "view",
      "type": "function"
    },
    {
      "inputs": [
        {
          "internalType": "address",
          "name": "",
          "type": "address"
        }
      ],
      "name": "winClaimed",
      "outputs": [
        {
          "internalType": "bool",
          "name": "",
          "type": "bool"
        }
      ],
      "stateMutability": "view",
      "type": "function"
    },
    {
      "inputs": [
        {
          "internalType": "address",
          "name": "escrow_",
          "type": "address"
        }
      ],
      "name": "changeEscrow",
      "outputs": [],
      "stateMutability": "nonpayable",
      "type": "function"
    },
    {
      "inputs": [
        {
          "internalType": "uint256",
          "name": "amount",
          "type": "uint256"
        },
        {
          "internalType": "uint256",
          "name": "seed",
          "type": "uint256"
        }
      ],
      "name": "spin",
      "outputs": [],
      "stateMutability": "nonpayable",
      "type": "function"
    },
    {
      "inputs": [],
      "name": "claimWin",
      "outputs": [],
      "stateMutability": "nonpayable",
      "type": "function"
    }
  ]